kbatch_papermill/__init__.py
kbatch_papermill/_job.py
kbatch_papermill/_kbatch.py
kbatch_papermill/_papermill.py
kbatch_papermill-0.1.0a1.dist-info/LICENSE
kbatch_papermill-0.1.0a1.dist-info/METADATA
kbatch_papermill-0.1.0a1.dist-info/WHEEL
kbatch_papermill-0.1.0a1.dist-info/top_level.txt
kbatch_papermill-0.1.0a1.dist-info/RECORD
