Metadata-Version: 2.2
Name: kbatch-papermill
Version: 0.1.0a1
Summary: KBatch Papermill: Run papermill in kbatch
Author-email: Min RK <benjaminrk@gmail.com>
License: BSD-3-Clause
Project-URL: Homepage, https://github.com/minrk/kbatch-papermill
Project-URL: Source, https://github.com/minrk/kbatch-papermill
Project-URL: Tracker, https://github.com/minrk/kbatch-papermill/issues
Keywords: Jupyter,Kubernetes
Classifier: Development Status :: 2 - Pre-Alpha
Classifier: Intended Audience :: Developers
Classifier: Intended Audience :: Science/Research
Classifier: License :: OSI Approved :: BSD License
Classifier: Programming Language :: Python
Classifier: Programming Language :: Python :: 3
Classifier: Operating System :: POSIX
Classifier: Framework :: Jupyter
Requires-Python: >=3.9
License-File: LICENSE
Requires-Dist: ipython
Requires-Dist: ipywidgets
Requires-Dist: kbatch
Requires-Dist: pyyaml
Requires-Dist: rich
Requires-Dist: s3fs
Requires-Dist: tqdm
Provides-Extra: test
Requires-Dist: pytest; extra == "test"
